[
    {
        "image": "https://media.themoviedb.org/t/p/w440_and_h660_face/f0lkDzdBxaW9nVJgAZq53Rz1Gmt.jpg",
        "category": "Pinoy Films",
        "title": "Once Before (2020)",
        "url": "https://pkaystream.cc/pl/MKT2dh4tMj/720?e="
    },
    {
        "image": "https://media.themoviedb.org/t/p/w440_and_h660_face/mjIrh2R4VLZAhI9bpJsjwkhwhHd.jpg",
        "category": "Pinoy Films",
        "title": "How to Be Yours (2016)",
        "url": "https://pkaystream.cc/pl/6yhoVMjVNm/720?e="
    },
    {
        "image": "https://media.themoviedb.org/t/p/w440_and_h660_face/6bakHIClWEzxddMoUelfiZX5B6.jpg",
        "category": "Pinoy Films",
        "title": "Girlfriend Na Pwede Na (2023)",
        "url": "https://pkaystream.cc/pl/yR4iJ1KA7J/720?e="
    },
    {
        "image": "https://media.themoviedb.org/t/p/w440_and_h660_face/zgaRu1fNiMF3axvlOLh3Nns8UIG.jpg",
        "category": "Pinoy Films",
        "title": "Between Maybes (2019)",
        "url": "https://pkaystream.cc/pl/Xf4dbvJC9s/720?e="
    },
    {
        "title": "Metro Manila",
        "url": "http://103.236.179.86:80/movie/rictms/rictms/8880.mp4"
    }
]