[
    {
        "title": "The Entitled",
        "url": "http://103.236.179.86:80/movie/rictms/rictms/7265.mp4"
    },
    {
        "image": "https://media.themoviedb.org/t/p/w440_and_h660_face/liQ2ZfQpSMnGGeH5Avi7UldJpkO.jpg",
        "category": "Pinoy Films",
        "title": "Moro (2023)",
        "url": "https://flashstream.cc/pl/JoMrpkhvgX/0-0?e="
    },
    {
        "image": "https://media.themoviedb.org/t/p/w440_and_h660_face/rUlMsLiL1iUvqE8YYwog0KPz6sV.jpg",
        "category": "Pinoy Films",
        "title": "Can We Still Be Friends? (2017)",
        "url": "https://flashstream.cc/pl/CmDLqEjMb0/0-0?e="
    },
    {
        "title": "Fortunato Salas: Kilabot Ng Pampanga",
        "url": "https://jungotvmedia.chanall.tv/jungotv/SOLARFortunatoSalasKilabotngPampangaTGFull25mbps/playlist.m3u8"
    },
    {
        "image": "https://media.themoviedb.org/t/p/w440_and_h660_face/fbxjz62fx584tHmUh3ZWBgOusIL.jpg",
        "category": "Pinoy Films",
        "title": "Will You Marry? (2021)",
        "url": "https://flashstream.cc/pl/shsMtBcEJK/0-0?e="
    }
]