[
    {
        "title": "Hello, Love, Goodbye",
        "url": "http://103.236.179.86:80/movie/rictms/rictms/8883.mp4"
    },
    {
        "title": "Atelophobia 2 (Dubbed in Tagalog)",
        "url": "https://jungotvmedia.chanall.tv/jungotv/ITNATELOPHOBIA2TGPHFullLowbit/playlist.m3u8"
    },
    {
        "title": "Mang Kepweng: The Mystery of the Dark Kerchief",
        "url": "http://103.236.179.86:80/movie/rictms/rictms/124.mp4"
    },
    {
        "title": "The Fearless Hyena (Dubbed in Tagalog)",
        "url": "https://jungotvmedia.chanall.tv/jungotv/DIMFearlessHyenaTGFULL10mbps/playlist.m3u8"
    },
    {
        "title": "Iskrokotoy",
        "url": "https://jungotvmedia.chanall.tv/jungotv/SOLARISKOROKOTOYTGFULL10mbps/playlist.m3u8"
    }
]