[
    {
        "image": "https://media.themoviedb.org/t/p/w440_and_h660_face/mym5bjjs8QcwzOtzbeKf1r6PEOg.jpg",
        "category": "Pinoy Films",
        "title": "The Cradle of the Brave (2023)",
        "url": "https://flashstream.cc/pl/eQPKW2fmCy/0-0?e="
    },
    {
        "image": "https://media.themoviedb.org/t/p/w440_and_h660_face/feaXwpthc6NAzfYI9WBt3Kq8bZT.jpg",
        "category": "Pinoy Films",
        "title": "You Are the Apple of My Eye (2019)",
        "url": "https://flashstream.cc/pl/LolLA6mkpm/0-0?e="
    },
    {
        "title": "Gorio Punasan: Rebel Driver",
        "url": "https://jungotvmedia.chanall.tv/jungotv/SOLARGorioPunasanRebelDriverTGFull15mbps/playlist.m3u8"
    },
    {
        "title": "The Fighting Mayor",
        "url": "https://jungotvmedia.chanall.tv/jungotv/SOLARTheFightingMayorTGFull15mbps/playlist.m3u8"
    },
    {
        "title": "Norte, The End of History",
        "url": "http://103.236.179.86:80/movie/rictms/rictms/8882.mp4"
    }
]