[
    {
        "image": "https://media.themoviedb.org/t/p/w440_and_h660_face/i8UjdAwezeFHHR4opNb3LxDCQWC.jpg",
        "category": "Pinoy Films",
        "title": "Rewind (2023)",
        "url": "https://flashstream.cc/pl/RJGLvLxlXT/0-0?e="
    },
    {
        "image": "https://media.themoviedb.org/t/p/w440_and_h660_face/5CjDuIQRlYcyzDeFsKIy9F8n9L8.jpg",
        "category": "Pinoy Films",
        "title": "Baler (2008)",
        "url": "https://flashstream.cc/pl/Het5I9h9D-/0-0?e="
    },
    {
        "image": "https://media.themoviedb.org/t/p/w440_and_h660_face/ggz4jp0B0OnM3TIC7sdfsHFb4o5.jpg",
        "category": "Pinoy Films",
        "title": "Sukob (2006)",
        "url": "https://flashstream.cc/pl/g79V6IftGP/0-0?e="
    },
    {
        "image": "https://media.themoviedb.org/t/p/w440_and_h660_face/7dKxw6UqKCmMCdW4k1tTYeej2rl.jpg",
        "category": "Pinoy Films",
        "title": "Hija (2021)",
        "url": "https://flashstream.cc/pl/EjLt8uVCpR/0-0?e="
    },
    {
        "image": "https://media.themoviedb.org/t/p/w440_and_h660_face/5Qiiq88ynNvufkGUmTQ2Lc5Yejs.jpg",
        "category": "Pinoy Films",
        "title": "Fatal Vacation (1990)",
        "url": "https://flashstream.cc/pl/GDWaiA2LCm/0-0?e="
    }
]