[
    {
        "image": "https://image.tmdb.org/t/p/w500/a2KwBZqjyhBmWFmifZWJS8UO2M1.jpg",
        "category": "Pinoy Films",
        "title": "The Fabulous Filipino Brothers (2021)",
        "url": "http://scrennnifu.click/movie/tt10810850/playlist.m3u8"
    },
    {
        "image": "https://image.tmdb.org/t/p/w500/sJFouUfCgHFSUh5OKVSQBSfrfA1.jpg",
        "category": "Pinoy Films",
        "title": "Goodbye (2019)",
        "url": "http://scrennnifu.click/movie/tt10156112/playlist.m3u8"
    },
    {
        "image": "https://image.tmdb.org/t/p/w500/xj06CIlkAsozJAbl8Ovw2aXCg29.jpg",
        "category": "Pinoy Films",
        "title": "Finding Agnes (2020)",
        "url": "http://scrennnifu.click/movie/tt13328840/playlist.m3u8"
    },
    {
        "image": "https://image.tmdb.org/t/p/w500/nkuph38pXE0yrGhnNtaO8xmR1v1.jpg",
        "category": "Pinoy Films",
        "title": "Espantaho (2025)",
        "url": "http://scrennnifu.click/movie/tt34830387/playlist.m3u8"
    },
    {
        "image": "https://image.tmdb.org/t/p/w500/cAnSL6yfojpf22Cy4dwNcaAF0rB.jpg",
        "category": "Pinoy Films",
        "title": "Love at First Stream (2021)",
        "url": "http://scrennnifu.click/movie/tt15006444/playlist.m3u8"
    },
    {
        "image": "https://image.tmdb.org/t/p/w500/u7HNcXZDsf2fhWdgQhLZnSBnc1g.jpg",
        "category": "Pinoy Films",
        "title": "Easter Sunday (2022)",
        "url": "http://scrennnifu.click/movie/tt11952606/playlist.m3u8"
    },
    {
        "image": "https://image.tmdb.org/t/p/w500/pKUEXWLEBxV7NnjIdr4yWzcuTUI.jpg",
        "category": "Pinoy Films",
        "title": "Respeto (2017)",
        "url": "http://scrennnifu.click/movie/tt7149134/playlist.m3u8"
    },
    {
        "image": "https://image.tmdb.org/t/p/w500/vvArzms4uGDAlqo6JfeAe0b4ro4.jpg",
        "category": "Pinoy Films",
        "title": "BuyBust (2018)",
        "url": "http://scrennnifu.click/movie/tt5938084/playlist.m3u8"
    },
    {
        "image": "https://image.tmdb.org/t/p/w500/pzJcGBMCxqoMH3QpQjlXeQBLjQc.jpg",
        "category": "Pinoy Films",
        "title": "Deleter (2022)",
        "url": "http://scrennnifu.click/movie/tt21237578/playlist.m3u8"
    },
    {
        "image": "https://image.tmdb.org/t/p/w500/hYGADLbf0I7VLe5i8pwjJ9dRYh4.jpg",
        "category": "Pinoy Films",
        "title": "Doll House (2022)",
        "url": "http://scrennnifu.click/movie/tt22038236/playlist.m3u8"
    },
    {
        "image": "https://image.tmdb.org/t/p/w500/8EuKlaYo53CDFAKbxzkQ8r2bSUP.jpg",
        "category": "Pinoy Films",
        "title": "Birdshot (2017)",
        "url": "http://scrennnifu.click/movie/tt6135042/playlist.m3u8"
    },
    {
        "image": "https://image.tmdb.org/t/p/w500/duEI37Qjtt1WaiOzZzVlkI6JO2z.jpg",
        "category": "Pinoy Films",
        "title": "Eerie (2019)",
        "url": "http://scrennnifu.click/movie/tt8723216/playlist.m3u8"
    },
    {
        "image": "https://image.tmdb.org/t/p/w500/sUeTYDwKYf9Lmhy3Ky2C8GjHuSY.jpg",
        "category": "Pinoy Films",
        "title": "Universe! (2023)",
        "url": "http://scrennnifu.click/movie/tt26426514/playlist.m3u8"
    },
    {
        "image": "https://image.tmdb.org/t/p/w500/kz0jM9Uw15ElDXQSpfNQupZuLPI.jpg",
        "category": "Pinoy Films",
        "title": "Seasons (2023)",
        "url": "http://scrennnifu.click/movie/tt28022861/playlist.m3u8"
    },
    {
        "image": "https://image.tmdb.org/t/p/w500/44oUwH7mn46IaOxIv8t9t5ckwW3.jpg",
        "category": "Pinoy Films",
        "title": "Keys to the Heart (2023)",
        "url": "http://scrennnifu.click/movie/tt29025883/playlist.m3u8"
    }
]