[
    {
        "title": "Hello, Love, Again",
        "url": "http://103.236.179.86:80/movie/rictms/rictms/15620.mp4"
    },
    {
        "image": "https://media.themoviedb.org/t/p/w440_and_h660_face/28H3Adz7CnNAuzsjL9P61kndUb3.jpg",
        "category": "Pinoy Films",
        "title": "The Entity (2019)",
        "url": "https://flashstream.cc/pl/VZdhyJbaWn/0-0?e="
    },
    {
        "image": "https://media.themoviedb.org/t/p/w440_and_h660_face/vl3MMPcYMVhSmoyby3eaI6CPbGT.jpg",
        "category": "Pinoy Films",
        "title": "The Super Parental Guardians (2016)",
        "url": "https://flashstream.cc/pl/8AAVoSTubi/0-0?e="
    },
    {
        "image": "https://media.themoviedb.org/t/p/w440_and_h660_face/hpuDoV3npVRpWdO96PRbgvlGMJe.jpg",
        "category": "Pinoy Films",
        "title": "Aswang (2019)",
        "url": "https://flashstream.cc/pl/GpmgmXpGoo/0-0?e="
    },
    {
        "image": "https://media.themoviedb.org/t/p/w440_and_h660_face/3yVrnuBH1cV1APK80BijYrru32e.jpg",
        "category": "Pinoy Films",
        "title": "Pagpag 24/7 (2024)",
        "url": "https://flashstream.cc/pl/wL86AeX8LC/0-0?e="
    }
]