[
    {
        "image": "https://media.themoviedb.org/t/p/w440_and_h660_face/tEDwm1r4mfVJbPz53rMPcW3C4L2.jpg",
        "category": "Pinoy Films",
        "title": "Broken Blooms (2022)",
        "url": "https://pkaystream.cc/pl/ji99Q2da7E/720?e="
    },
    {
        "image": "https://media.themoviedb.org/t/p/w440_and_h660_face/98NynscUUYUcNbwY1NLAhjPBsCt.jpg",
        "category": "Pinoy Films",
        "title": "Mary, Marry Me (2018)",
        "url": "https://pkaystream.cc/pl/qI-LXUxlL5/720?e="
    },
    {
        "image": "https://media.themoviedb.org/t/p/w440_and_h660_face/89jXZYnP7RB6xTHhZCMUxk14HaZ.jpg",
        "category": "Pinoy Films",
        "title": "A Second Chance (2015)",
        "url": "https://pkaystream.cc/pl/nVau7knYEY/720?e="
    },
    {
        "image": "https://media.themoviedb.org/t/p/w440_and_h660_face/10AaeA1oQCsVVCXUb6SrZc7nw9j.jpg",
        "category": "Pinoy Films",
        "title": "40 (2024)",
        "url": "https://pkaystream.cc/pl/MM9bS6qrvh/720?e="
    },
    {
        "image": "https://media.themoviedb.org/t/p/w440_and_h660_face/wQ80tPzGP5gnrtoXV9JFWVlQVJL.jpg",
        "category": "Pinoy Films",
        "title": "Un/Happy for You (2024)",
        "url": "https://pkaystream.cc/pl/O54uhPcS0s/720?e="
    }
]