[
    {
        "image": "https://image.tmdb.org/t/p/w500/zFbC5LeySM8rVU52dHA7sr5AH9o.jpg",
        "category": "Pinoy Films",
        "title": "Ang Pangarap kong Oskars (2023)",
        "url": "http://scrennnifu.click/movie/tt28252817/playlist.m3u8"
    },
    {
        "image": "https://image.tmdb.org/t/p/w500/sUeTYDwKYf9Lmhy3Ky2C8GjHuSY.jpg",
        "category": "Pinoy Films",
        "title": "Universe! (2023)",
        "url": "http://scrennnifu.click/movie/tt26426514/playlist.m3u8"
    },
    {
        "image": "https://image.tmdb.org/t/p/w500/7R940b9RNNKLDrAI1GmCjOd5ta.jpg",
        "category": "Pinoy Films",
        "title": "Again (2024)",
        "url": "http://scrennnifu.click/movie/tt32401874/playlist.m3u8"
    },
    {
        "image": "https://image.tmdb.org/t/p/w500/zJ1ePsQmB984EvTOaKXfIliKsCV.jpg",
        "category": "Pinoy Films",
        "title": "Maria (2019)",
        "url": "http://scrennnifu.click/movie/tt7594584/playlist.m3u8"
    },
    {
        "image": "https://image.tmdb.org/t/p/w500/jsWZqU9qtCOdBNoeU7u29D0yet0.jpg",
        "category": "Pinoy Films",
        "title": "Reroute (2022)",
        "url": "http://scrennnifu.click/movie/tt16900304/playlist.m3u8"
    },
    {
        "image": "https://image.tmdb.org/t/p/w500/ezfxB7Kd2l6keH9xBCX4599zuuL.jpg",
        "category": "Pinoy Films",
        "title": "A Very Good Girl (2023)",
        "url": "http://scrennnifu.click/movie/tt27327494/playlist.m3u8"
    },
    {
        "image": "https://image.tmdb.org/t/p/w500/a2KwBZqjyhBmWFmifZWJS8UO2M1.jpg",
        "category": "Pinoy Films",
        "title": "The Fabulous Filipino Brothers (2021)",
        "url": "http://scrennnifu.click/movie/tt10810850/playlist.m3u8"
    },
    {
        "image": "https://image.tmdb.org/t/p/w500/fZuIWrzsqoeVlyWBJIek8crGSFz.jpg",
        "category": "Pinoy Films",
        "title": "Goyo: The Boy General (2018)",
        "url": "http://scrennnifu.click/movie/tt5094192/playlist.m3u8"
    },
    {
        "image": "https://image.tmdb.org/t/p/w500/i8UjdAwezeFHHR4opNb3LxDCQWC.jpg",
        "category": "Pinoy Films",
        "title": "Rewind (2023)",
        "url": "http://scrennnifu.click/movie/tt28152455/playlist.m3u8"
    },
    {
        "image": "https://image.tmdb.org/t/p/w500/oUK73m89HDkKTanRGrd8eEvuYHT.jpg",
        "category": "Pinoy Films",
        "title": "Ang Huling Henya (2013)",
        "url": "http://scrennnifu.click/movie/tt3138730/playlist.m3u8"
    },
    {
        "image": "https://image.tmdb.org/t/p/w500/pzJcGBMCxqoMH3QpQjlXeQBLjQc.jpg",
        "category": "Pinoy Films",
        "title": "Deleter (2022)",
        "url": "http://scrennnifu.click/movie/tt21237578/playlist.m3u8"
    },
    {
        "image": "https://image.tmdb.org/t/p/w500/pKUEXWLEBxV7NnjIdr4yWzcuTUI.jpg",
        "category": "Pinoy Films",
        "title": "Respeto (2017)",
        "url": "http://scrennnifu.click/movie/tt7149134/playlist.m3u8"
    },
    {
        "image": "https://image.tmdb.org/t/p/w500/u7HNcXZDsf2fhWdgQhLZnSBnc1g.jpg",
        "category": "Pinoy Films",
        "title": "Easter Sunday (2022)",
        "url": "http://scrennnifu.click/movie/tt11952606/playlist.m3u8"
    },
    {
        "image": "https://image.tmdb.org/t/p/w500/sJFouUfCgHFSUh5OKVSQBSfrfA1.jpg",
        "category": "Pinoy Films",
        "title": "Goodbye (2019)",
        "url": "http://scrennnifu.click/movie/tt10156112/playlist.m3u8"
    },
    {
        "image": "https://image.tmdb.org/t/p/w500/zsCbJ0N1nDTTntAVgUxEWCmlCh6.jpg",
        "category": "Pinoy Films",
        "title": "El Presidente (2012)",
        "url": "http://scrennnifu.click/movie/tt2477732/playlist.m3u8"
    }
]