[
    {
        "image": "https://media.themoviedb.org/t/p/w440_and_h660_face/zXsJZa7M43xJPS9l5Emcp1IxDOS.jpg",
        "category": "Pinoy Films",
        "title": "The Ghost Bride (2017)",
        "url": "https://flashstream.cc/pl/GByexFqYQo/0-0?e="
    },
    {
        "title": "Losers-1, Sucker-0",
        "url": "http://103.236.179.86:80/movie/rictms/rictms/502.mp4"
    },
    {
        "image": "https://media.themoviedb.org/t/p/w440_and_h660_face/plv85l002BHwPq7zvjceGt4h3nz.jpg",
        "category": "Pinoy Films",
        "title": "The Entitled (2022)",
        "url": "https://flashstream.cc/pl/rg0IK9f4B2/0-0?e="
    },
    {
        "title": "Men Are From QC, Women Are From Alabang",
        "url": "http://103.236.179.86:80/movie/rictms/rictms/12790.mp4"
    },
    {
        "image": "https://media.themoviedb.org/t/p/w440_and_h660_face/44oUwH7mn46IaOxIv8t9t5ckwW3.jpg",
        "category": "Pinoy Films",
        "title": "Keys to the Heart (2023)",
        "url": "https://flashstream.cc/pl/9swb4tor1V/0-0?e="
    }
]