[
    {
        "image": "https://media.themoviedb.org/t/p/w440_and_h660_face/kyLu1gq6R9MXsvb0yjmvNU90aWB.jpg",
        "category": "Pinoy Films",
        "title": "Nanahimik ang Gabi (2022)",
        "url": "https://flashstream.cc/pl/K0XqOyqrHH/0-0?e="
    },
    {
        "title": "Hello, Love, Again",
        "url": "http://103.236.179.86:80/movie/rictms/rictms/15620.mp4"
    },
    {
        "image": "https://media.themoviedb.org/t/p/w440_and_h660_face/29IpnkqWIkFvSlynGu7X6ylAdiL.jpg",
        "category": "Pinoy Films",
        "title": "Ballot (2024)",
        "url": "https://flashstream.cc/pl/lALprfvjzr/0-0?e="
    },
    {
        "title": "Sindak!",
        "url": "https://jungotvmedia.chanall.tv/jungotv/SOLARSindakTGFULL10mbps/playlist.m3u8"
    },
    {
        "image": "https://media.themoviedb.org/t/p/w440_and_h660_face/hAVB8gjDAMvb6eu0UgUtXnXCMd7.jpg",
        "category": "Pinoy Films",
        "title": "Green Bones (2024)",
        "url": "https://flashstream.cc/pl/ffHTACYuF0/0-0?e="
    }
]