[
    {
        "title": "Ang Sumpa ng Sirena (The Mermaid's Curse)",
        "url": "https://jungotvmedia.chanall.tv/jungotv/ITNTheMermaidsCurseTGFULL5mbps/playlist.m3u8"
    },
    {
        "image": "https://media.themoviedb.org/t/p/w440_and_h660_face/nlovfFBPkyfWxCutjb3vxxWBiZQ.jpg",
        "category": "Pinoy Films",
        "title": "Tuloy... Bukas ang Pinto (2022)",
        "url": "https://flashstream.cc/pl/qaV74tPmXq/720?e="
    },
    {
        "image": "https://media.themoviedb.org/t/p/w440_and_h660_face/gtgltT1u4kVUJBocfRb1Xf2v1gu.jpg",
        "category": "Pinoy Films",
        "title": "Mama Susan's Friends (2023)",
        "url": "https://flashstream.cc/pl/Nm3ndBzbvI/720?e="
    },
    {
        "title": "Isla Grande",
        "url": "https://jungotvmedia.chanall.tv/jungotv/SolarIslaGrandeFullTGPH/playlist.m3u8"
    },
    {
        "title": "Ang Babaeng Hinugot Sa Aking Tadyang",
        "url": "https://jungotvmedia.chanall.tv/jungotv/SOLARANGBABAINGHINUGOTSAAKINGTADYANGFULL10mbps/playlist.m3u8"
    }
]