[
    {
        "image": "https://media.themoviedb.org/t/p/w440_and_h660_face/nchHIUYqFXD5q4Xp5DVj7NCxhIr.jpg",
        "category": "Pinoy Films",
        "title": "You Changed My Life (2009)",
        "url": "https://flashstream.cc/pl/EWB_I8rd-W/0-0?e="
    },
    {
        "image": "https://media.themoviedb.org/t/p/w440_and_h660_face/kogK99QugddnSIMe3Wy8fWCLL60.jpg",
        "category": "Pinoy Films",
        "title": "Ten Little Mistresses (2023)",
        "url": "https://flashstream.cc/pl/R16KOwkJFK/0-0?e="
    },
    {
        "title": "Ang Babaeng Hinugot Sa Aking Tadyang",
        "url": "https://jungotvmedia.chanall.tv/jungotv/SOLARANGBABAINGHINUGOTSAAKINGTADYANGFULL10mbps/playlist.m3u8"
    },
    {
        "image": "https://media.themoviedb.org/t/p/w440_and_h660_face/p94GMxCeven6DVqo8ztPx2SV9bk.jpg",
        "category": "Pinoy Films",
        "title": "Third World Romance (2023)",
        "url": "https://flashstream.cc/pl/lyS6xn05c4/0-0?e="
    },
    {
        "image": "https://media.themoviedb.org/t/p/w440_and_h660_face/hAVB8gjDAMvb6eu0UgUtXnXCMd7.jpg",
        "category": "Pinoy Films",
        "title": "Green Bones (2024)",
        "url": "https://flashstream.cc/pl/ffHTACYuF0/0-0?e="
    }
]